stocktwits_collector/__init__.py
stocktwits_collector/collector.py
stocktwits_collector/signals.py
stocktwits_collector/streamer.py
tests/__init__.py
tests/integration_test.py
tests/test_collector.py
tests/test_signals.py
stocktwits_collector-0.3.2.dist-info/LICENSE
stocktwits_collector-0.3.2.dist-info/METADATA
stocktwits_collector-0.3.2.dist-info/WHEEL
stocktwits_collector-0.3.2.dist-info/top_level.txt
stocktwits_collector-0.3.2.dist-info/RECORD
