Metadata-Version: 2.1
Name: stocktwits-collector
Version: 0.3.2
Summary: Stocktwits collector Python package
Home-page: https://stocktwits-collector.readthedocs.io/
Author: Alessandra Bilardi
Author-email: alessandra.bilardi@gmail.com
Project-URL: Source, https://github.com/bilardi/stocktwits-collector
Project-URL: Bug Reports, https://github.com/bilardi/stocktwits-collector/issues
Project-URL: Funding, https://donate.pypi.org
Classifier: Programming Language :: Python :: 3
Classifier: License :: OSI Approved :: MIT License
Classifier: Operating System :: OS Independent
Requires-Python: >=3.6
License-File: LICENSE
